axon_velocity/__init__.py
axon_velocity/axon_velocity.py
axon_velocity/evaluation.py
axon_velocity/models.py
axon_velocity/plotting.py
axon_velocity/tools.py
axon_velocity/tracking_classes.py
axon_velocity/version.py
axon_velocity-0.1.2.dist-info/LICENSE
axon_velocity-0.1.2.dist-info/METADATA
axon_velocity-0.1.2.dist-info/WHEEL
axon_velocity-0.1.2.dist-info/top_level.txt
axon_velocity-0.1.2.dist-info/RECORD
