Metadata-Version: 2.1
Name: axon-velocity
Version: 0.1.2
Summary: Python package to reconstruct axonal branches from high-density micro-electrode array data
Home-page: https://github.com/alejoe91/axon_velocity
Author: Alessio Buccino, Xinyue Yuan
Author-email: alessiop.buccino@gmail.com
License: UNKNOWN
Platform: UNKNOWN
Classifier: Programming Language :: Python :: 3
Classifier: License :: OSI Approved :: GNU General Public License v3 (GPLv3)
Classifier: Operating System :: OS Independent
Requires-Dist: numpy
Requires-Dist: matplotlib
Requires-Dist: scipy
Requires-Dist: networkx
Requires-Dist: sklearn
Requires-Dist: MEAutility
Requires-Dist: probeinterface
